{
	"format_version": "1.8.0",
	"animations": {
		"parasite_idle": {
			"loop": true,
			"animation_length": 1.04,
			"bones": {
				"body": {
					"rotation": {
						"0.0": [0, 0, 0],
						"0.52": [-12.5, 0, 0],
						"1.04": [0, 0, 0]
					}
				},
				"parahead": {
					"rotation": {
						"0.0": [0, 0, 0],
						"0.52": [-15, 0, 0],
						"1.04": [0, 0, 0]
					}
				},
				"a": {
					"rotation": {
						"0.0": [0, 0, 0],
						"0.24": [0, 15, 0],
						"0.8": [0, -15, 0],
						"1.04": [0, 0, 0]
					}
				},
				"b": {
					"rotation": {
						"0.0": [0, 0, 0],
						"0.52": [20, 0, 0],
						"1.04": [0, 0, 0]
					}
				},
				"c": {
					"rotation": {
						"0.0": [0, 0, 0],
						"0.36": [0, 10, 0],
						"0.68": [0, -10, 0],
						"1.04": [0, 0, 0]
					}
				},
				"d": {
					"rotation": {
						"0.0": [0, 0, 0],
						"0.48": [0, 0, 30],
						"1.04": [0, 0, 0]
					}
				},
				"mega_jaw": {
					"rotation": {
						"0.0": [0, 0, 0],
						"1.04": [0, 0, 360]
					}
				},
				"claw": {
					"rotation": {
						"0.0": [0, 0, 0],
						"0.4": [0, 60, 0],
						"0.52": [0, -10, 0],
						"1.04": [0, 0, 0]
					}
				},
				"claw3": {
					"rotation": {
						"0.0": [0, 0, 0],
						"0.4": [-60, 0, 0],
						"0.52": [10, 0, 0],
						"1.04": [0, 0, 0]
					}
				},
				"claw4": {
					"rotation": {
						"0.0": [0, 0, 0],
						"0.4": [60, 0, 0],
						"0.52": [-10, 0, 0],
						"1.04": [0, 0, 0]
					}
				},
				"claw2": {
					"rotation": {
						"0.0": [0, 0, 0],
						"0.4": [0, -60, 0],
						"0.52": [0, 10, 0],
						"1.04": [0, 0, 0]
					}
				},
				"a2": {
					"rotation": {
						"0.0": [0, 0, 0],
						"0.12": [10, 0, 0],
						"0.72": [-40, 0, 0],
						"1.04": [0, 0, 0]
					}
				},
				"b2": {
					"rotation": {
						"0.0": [0, 0, 0],
						"0.12": [30, 0, 0],
						"0.72": [-30, 0, 0],
						"1.04": [0, 0, 0]
					}
				},
				"c2": {
					"rotation": {
						"0.0": [0, 0, 0],
						"0.12": [25, 0, 0],
						"0.72": [-30, 0, 0],
						"1.04": [0, 0, 0]
					}
				},
				"d2": {
					"rotation": {
						"0.0": [0, 0, 0],
						"0.12": [75, 0, 0],
						"0.72": [-30, 0, 0],
						"1.04": [0, 0, 0]
					}
				},
				"a3": {
					"rotation": {
						"0.0": [0, 0, 0],
						"0.24": [10, 0, 0],
						"0.84": [-40, 0, 0],
						"1.04": [0, 0, 0]
					}
				},
				"b3": {
					"rotation": {
						"0.0": [0, 0, 0],
						"0.24": [30, 0, 0],
						"0.84": [-30, 0, 0],
						"1.04": [0, 0, 0]
					}
				},
				"c3": {
					"rotation": {
						"0.0": [0, 0, 0],
						"0.24": [25, 0, 0],
						"0.84": [-30, 0, 0],
						"1.04": [0, 0, 0]
					}
				},
				"d3": {
					"rotation": {
						"0.0": [0, 0, 0],
						"0.24": [75, 0, 0],
						"0.84": [-30, 0, 0],
						"1.04": [0, 0, 0]
					}
				},
				"a4": {
					"rotation": {
						"0.0": [0, 0, 0],
						"0.52": [0, 15, 0],
						"1.04": [0, 0, 0]
					}
				},
				"b4": {
					"rotation": {
						"0.0": [0, 0, 0],
						"0.52": [0, -15, 0],
						"1.04": [0, 0, 0]
					}
				},
				"c4": {
					"rotation": {
						"0.0": [0, 0, 0],
						"0.52": [0, -27.5, 0],
						"1.04": [0, 0, 0]
					}
				},
				"d4": {
					"rotation": {
						"0.0": [0, 0, 0],
						"0.52": [0, -37.5, 0],
						"1.04": [0, 0, 0]
					}
				},
				"a5": {
					"rotation": {
						"0.0": [0, 0, 0],
						"0.4": [0, -15, 0],
						"1.04": [0, 0, 0]
					}
				},
				"b5": {
					"rotation": {
						"0.0": [0, 0, 0],
						"0.4": [0, 15, 0],
						"1.04": [0, 0, 0]
					}
				},
				"c5": {
					"rotation": {
						"0.0": [0, 0, 0],
						"0.4": [0, 27.5, 0],
						"1.04": [0, 0, 0]
					}
				},
				"d5": {
					"rotation": {
						"0.0": [0, 0, 0],
						"0.4": [0, 37.5, 0],
						"1.04": [0, 0, 0]
					}
				},
				"head": {
					"rotation": {
						"0.0": [0, 0, 0],
						"0.24": [0, 20, 0],
						"0.84": [0, -20, 0],
						"1.04": [0, 0, 0]
					}
				},
				"jaw_up": {
					"rotation": [-45, 0, 0]
				},
				"jaw_down": {
					"rotation": [45, 0, 0]
				}
			}
		},
		"idle": {
			"loop": true,
			"animation_length": 1.04,
			"bones": {
				"body": {
					"rotation": {
						"0.0": [0, 0, 0],
						"0.52": [10, 0, 0],
						"1.04": [0, 0, 0]
					}
				},
				"upperBody": {
					"rotation": {
						"0.0": [0, 0, 0],
						"0.52": [-5, 0, 0],
						"1.04": [0, 0, 0]
					}
				}
			}
		},
		"cute_eyes": {
			"loop": true,
			"animation_length": 0.52,
			"bones": {
				"eye": {
					"scale": {
						"0.0": [1, 1, 1],
						"0.12": [0.9, 0.9, 0.9],
						"0.4": [1.075, 1.075, 1.075],
						"0.52": [1, 1, 1]
					}
				},
				"eye2": {
					"scale": {
						"0.0": [1, 1, 1],
						"0.12": [0.9, 0.9, 0.9],
						"0.4": [1.075, 1.075, 1.075],
						"0.52": [1, 1, 1]
					}
				}
			}
		},
		"floof": {
			"loop": true,
			"animation_length": 1.04,
			"bones": {
				"tail": {
					"rotation": {
						"0.0": [0, 0, 0],
						"0.16": [-10, 0, 0],
						"0.52": [-45, 0, 0],
						"0.84": [-10, 0, 0],
						"1.04": [0, 0, 0]
					}
				},
				"ear": {
					"rotation": {
						"0.0": [0, 0, 0],
						"0.28": [-10, 0, 0],
						"0.8": [10, 0, 0],
						"1.04": [0, 0, 0]
					}
				},
				"ear2": {
					"rotation": {
						"0.0": [0, 0, 0],
						"0.28": [10, 0, 0],
						"0.8": [-10, 0, 0],
						"1.04": [0, 0, 0]
					}
				},
				"tail3": {
					"rotation": {
						"0.0": [0, 0, 0],
						"0.52": [-12.5, 0, 0],
						"1.04": [0, 0, 0]
					}
				},
				"tail2": {
					"rotation": {
						"0.0": [0, 0, 0],
						"0.2": [0, 0, 10],
						"0.52": [0, 0, 0],
						"0.84": [0, 0, -10],
						"1.04": [0, 0, 0]
					}
				}
			}
		},
		"transform": {
			"animation_length": 1.28,
			"bones": {
				"body": {
					"rotation": {
						"0.0": [0, 0, 0],
						"0.16": [0, -2, 2],
						"0.24": [0, 2, 2],
						"0.32": [0, 0, -2],
						"0.4": [-2, 0, 0],
						"0.48": [0, -2, 2],
						"0.56": [0, 2, 2],
						"0.64": [0, 0, -2],
						"0.72": [-2, 0, 0],
						"0.8": [0, 0, 0]
					}
				},
				"head": {
					"rotation": {
						"0.0": [0, 0, 0],
						"0.08": [0, -15, 15],
						"0.16": [0, 15, 15],
						"0.24": [0, 0, -30],
						"0.32": [-15, 0, 0],
						"0.4": [0, -30, 30],
						"0.48": [0, 15, 15],
						"0.56": [0, 0, -15],
						"0.64": [-15, 0, 0],
						"0.72": [0, 0, 0]
					}
				},
				"jaw_up": {
					"rotation": {
						"0.0": [0, 0, 0],
						"0.28": [-45, 0, 0]
					}
				},
				"jaw_down": {
					"rotation": {
						"0.0": [0, 0, 0],
						"0.28": [45, 0, 0]
					}
				},
				"parahead": {
					"rotation": {
						"0.64": [0, 0, 0],
						"1.24": [0, 0, 0]
					},
					"position": {
						"0.0": [0, 0, 14],
						"0.28": [0, 0, 4],
						"0.64": [0, 0, 0],
						"1.24": [0, 0, 0]
					},
					"scale": {
						"0.0": [0, 0, 0],
						"0.28": [0, 0, 0],
						"0.64": [1, 1, 1],
						"1.24": [1, 1, 1]
					}
				},
				"a": {
					"rotation": {
						"0.0": [0, 0, 0],
						"0.52": [0, -10, 0],
						"0.88": [-10, 0, 0],
						"1.04": [0, 0, 0]
					}
				},
				"b": {
					"rotation": {
						"0.0": [0, 0, 0],
						"0.52": [0, 0, 0],
						"0.68": [-10, 15, -3],
						"0.88": [10, -15, -3],
						"1.04": [0, 0, 0]
					}
				},
				"mega_jaw": {
					"rotation": {
						"0.48": [0, 0, 0],
						"1.0": [0, 0, 360]
					}
				},
				"claw": {
					"rotation": {
						"0.0": [0, 0, 0],
						"0.88": [0, 0, 0],
						"1.0": [0, 30, 0],
						"1.16": [0, -10, 0],
						"1.28": [0, 0, 0]
					}
				},
				"claw3": {
					"rotation": {
						"0.0": [0, 0, 0],
						"0.88": [0, 0, 0],
						"1.0": [-30, 0, 0],
						"1.16": [10, 0, 0],
						"1.28": [0, 0, 0]
					}
				},
				"claw4": {
					"rotation": {
						"0.0": [0, 0, 0],
						"0.88": [0, 0, 0],
						"1.0": [30, 0, 0],
						"1.16": [-10, 0, 0],
						"1.28": [0, 0, 0]
					}
				},
				"claw2": {
					"rotation": {
						"0.0": [0, 0, 0],
						"0.88": [0, 0, 0],
						"1.0": [0, -30, 0],
						"1.16": [0, 10, 0],
						"1.28": [0, 0, 0]
					}
				},
				"parahand1": {
					"position": {
						"0.0": [-5, 0, 5],
						"0.52": [0, 0, 0],
						"1.24": [0, 0, 0]
					},
					"scale": {
						"0.0": [0, 0, 0],
						"0.52": [1, 1, 1],
						"1.24": [1, 1, 1]
					}
				},
				"c2": {
					"rotation": {
						"0.48": [0, 0, 0],
						"0.6": [-30, 0, 0],
						"0.76": [20, 0, 0],
						"0.84": [0, 0, 0]
					}
				},
				"parahand2": {
					"position": {
						"0.0": [5, 0, 5],
						"0.28": [0, 0, 0],
						"1.24": [0, 0, 0]
					},
					"scale": {
						"0.0": [0, 0, 0],
						"0.28": [1, 1, 1],
						"1.24": [1, 1, 1]
					}
				},
				"c3": {
					"rotation": {
						"0.2": [0, 0, 0],
						"0.32": [-30, 0, 0],
						"0.48": [20, 0, 0],
						"0.56": [0, 0, 0]
					}
				},
				"parahand3": {
					"position": {
						"0.0": [5, 0, 5],
						"0.52": [0, 0, 0],
						"1.24": [0, 0, 0]
					},
					"scale": {
						"0.0": [0, 0, 0],
						"0.52": [1, 1, 1],
						"1.24": [1, 1, 1]
					}
				},
				"c4": {
					"rotation": {
						"0.44": [0, 0, 0],
						"0.56": [-30, 0, 0],
						"0.72": [20, 0, 0],
						"0.8": [0, 0, 0]
					}
				},
				"parahand4": {
					"position": {
						"0.0": [-5, 0, 5],
						"0.68": [0, 0, 0],
						"1.24": [0, 0, 0]
					},
					"scale": {
						"0.0": [0, 0, 0],
						"0.68": [1, 1, 1],
						"1.24": [1, 1, 1]
					}
				},
				"a5": {
					"rotation": {
						"0.0": [0, 0, 0],
						"0.52": [10, 0, 0],
						"0.68": [0, 0, 0],
						"0.8": [-20, 0, 0],
						"0.96": [0, 0, 0]
					}
				},
				"c5": {
					"rotation": {
						"0.68": [0, 0, 0],
						"0.8": [-30, 0, 0],
						"0.96": [20, 0, 0],
						"1.04": [0, 0, 0]
					}
				}
			}
		},
		"whining_start": {
			"animation_length": 0.48,
			"bones": {
				"leg3": {
					"rotation": {
						"0.2": [0, 0, 0],
						"0.36": [0, 0, -15],
						"0.48": [0, 0, 0]
					},
					"position": {
						"0.0": [0, 0, 0],
						"0.2": [0, 2, 0],
						"0.36": [0, 2, 0],
						"0.48": [0, 0, 0]
					}
				},
				"leg2": {
					"rotation": {
						"0.2": [0, 0, 0],
						"0.36": [0, 0, 15],
						"0.48": [0, 0, 0]
					},
					"position": {
						"0.0": [0, 0, 0],
						"0.2": [0, 2, 0],
						"0.36": [0, 2, 0],
						"0.48": [0, 0, 0]
					}
				},
				"body": {
					"rotation": {
						"0.0": [0, 0, 0],
						"0.12": [-20, 0, 0],
						"0.36": [-20, 0, 0],
						"0.48": [0, 0, 0]
					},
					"position": {
						"0.0": [0, 0, 0],
						"0.12": [0, 1, 0],
						"0.36": [0, 1, 0],
						"0.48": [0, 0, 0]
					}
				},
				"head": {
					"rotation": {
						"0.0": [0, 0, 0],
						"0.12": [0, 0, 0],
						"0.2": [0, 0, -25],
						"0.4": [0, 0, -25],
						"0.48": [0, 0, 0]
					}
				}
			}
		},
		"attack_0": {
			"animation_length": 1.04,
			"bones": {
				"leg3": {
					"rotation": {
						"0.0": [0, 0, 0],
						"0.52": [-25, 0, 0],
						"0.64": [-25, 0, 0],
						"0.72": [0, 0, 0]
					},
					"position": {
						"0.0": [0, 0, 0],
						"0.52": [0, 9, 5],
						"0.64": [0, 9, 5],
						"0.72": [0, 0, 0]
					}
				},
				"leg2": {
					"rotation": {
						"0.0": [0, 0, 0],
						"0.52": [-25, 0, 0],
						"0.64": [-25, 0, 0],
						"0.72": [0, 0, 0]
					},
					"position": {
						"0.0": [0, 0, 0],
						"0.52": [0, 9, 5],
						"0.64": [0, 9, 5],
						"0.72": [0, 0, 0]
					}
				},
				"body": {
					"rotation": {
						"0.0": [0, 0, 0],
						"0.52": [-60, 0, 0],
						"0.64": [-60, 0, 0],
						"0.72": [0, 0, 0],
						"1.04": [0, 0, 0]
					},
					"position": {
						"0.0": [0, 0, 0],
						"0.52": [0, 3, 4],
						"0.64": [0, 3, 4],
						"0.72": [0, 0, 0],
						"1.04": [0, 0, 0]
					}
				},
				"head": {
					"rotation": {
						"0.0": [0, 0, 0],
						"0.52": [-30, 0, 0],
						"0.64": [-30, 0, 0],
						"0.72": [0, 0, 0]
					},
					"position": {
						"0.0": [0, 0, 0],
						"0.52": [0, 2, 0],
						"0.64": [0, 2, 0],
						"0.72": [0, 0, 0]
					}
				},
				"a": {
					"rotation": {
						"0.0": [0, 0, 0],
						"0.52": [-10, 0, 0],
						"0.64": [-20, 0, 0],
						"0.72": [10, 0, 0],
						"0.8": [10, 0, 0],
						"1.04": [0, 0, 0]
					}
				},
				"b": {
					"rotation": {
						"0.0": [0, 0, 0],
						"0.52": [-10, 0, 0],
						"0.64": [-20, 0, 0],
						"0.72": [10, 0, 0],
						"0.8": [10, 0, 0],
						"1.04": [0, 0, 0]
					}
				},
				"c": {
					"rotation": {
						"0.0": [0, 0, 0],
						"0.52": [-30, 0, 0],
						"0.64": [-30, 0, 0],
						"0.72": [10, 0, 0],
						"0.8": [10, 0, 0],
						"1.04": [0, 0, 0]
					}
				},
				"d": {
					"rotation": {
						"0.0": [0, 0, 0],
						"0.52": [-30, 0, 0],
						"0.64": [-30, 0, 0],
						"0.72": [10, 0, 0],
						"0.8": [10, 0, 0],
						"1.04": [0, 0, 0]
					}
				},
				"claw": {
					"rotation": {
						"0.0": [0, 0, 0],
						"0.52": [0, 0, 0],
						"0.64": [0, 60, 0],
						"0.8": [0, 0, 0]
					}
				},
				"claw3": {
					"rotation": {
						"0.0": [0, 0, 0],
						"0.52": [0, 0, 0],
						"0.64": [-60, 0, 0],
						"0.8": [0, 0, 0]
					}
				},
				"claw4": {
					"rotation": {
						"0.0": [0, 0, 0],
						"0.52": [0, 0, 0],
						"0.64": [60, 0, 0],
						"0.8": [0, 0, 0]
					}
				},
				"claw2": {
					"rotation": {
						"0.0": [0, 0, 0],
						"0.52": [0, 0, 0],
						"0.64": [0, -60, 0],
						"0.8": [0, 0, 0]
					}
				}
			}
		},
		"attack_1": {
			"animation_length": 1.04,
			"bones": {
				"changeling": {
					"rotation": {
						"0.0": [0, 0, 0],
						"0.52": [0, -360, 0]
					},
					"position": {
						"0.0": [0, 0, 0],
						"0.16": [0, -5, 0],
						"0.52": [0, -2, 0],
						"0.6": [0, 0, 0]
					}
				},
				"leg3": {
					"rotation": {
						"0.0": [0, 0, 0],
						"0.16": [-80, 0, 0],
						"0.52": [-80, 0, 0],
						"0.6": [0, 0, 0]
					}
				},
				"leg2": {
					"rotation": {
						"0.0": [0, 0, 0],
						"0.16": [-80, 0, 0],
						"0.52": [-80, 0, 0],
						"0.6": [0, 0, 0]
					}
				},
				"leg0": {
					"rotation": {
						"0.0": [0, 0, 0],
						"0.16": [60, 0, 0],
						"0.52": [60, 0, 0],
						"0.6": [0, 0, 0]
					}
				},
				"leg1": {
					"rotation": {
						"0.0": [0, 0, 0],
						"0.16": [60, 0, 0],
						"0.52": [60, 0, 0],
						"0.6": [0, 0, 0]
					}
				}
			}
		},
		"attack_2": {
			"animation_length": 1.04,
			"bones": {
				"head": {
					"rotation": {
						"0.0": [0, 0, 0],
						"0.32": [-40, 0, 0],
						"0.44": [0, 0, 0]
					}
				},
				"b": {
					"rotation": {
						"0.0": [0, 0, 0],
						"0.32": [-95, 0, 0],
						"0.44": [0, 0, 0]
					}
				},
				"c": {
					"rotation": {
						"0.0": [0, 0, 0],
						"0.32": [57.5, 0, 0],
						"0.44": [0, 0, 0]
					}
				},
				"d": {
					"rotation": {
						"0.0": [0, 0, 0],
						"0.24": [44.06, 0, 0],
						"0.32": [60, 0, 0],
						"0.44": [0, 0, 0]
					}
				},
				"mega_jaw": {
					"rotation": {
						"0.0": [0, 0, 0],
						"0.32": [30, 0, 0],
						"0.44": [0, 0, 0]
					}
				},
				"claw": {
					"rotation": {
						"0.0": [0, 0, 0],
						"0.32": [0, 60, 0],
						"0.44": [0, 0, 0]
					}
				},
				"claw3": {
					"rotation": {
						"0.0": [0, 0, 0],
						"0.32": [-60, 0, 0],
						"0.44": [0, 0, 0]
					}
				},
				"claw4": {
					"rotation": {
						"0.0": [0, 0, 0],
						"0.32": [60, 0, 0],
						"0.44": [0, 0, 0]
					}
				},
				"claw2": {
					"rotation": {
						"0.0": [0, 0, 0],
						"0.32": [0, -60, 0],
						"0.44": [0, 0, 0]
					}
				}
			}
		}
	}
}